<exist xml:id="folkSong_06234_0194">
    <teiHeader xmlns="http://www.tei-c.org/ns/1.0">
		<fileDesc>
			<titleStmt>
				<title type="main">[Mikor élő voltam, élőket tápláltam; …]</title>
				<respStmt>
					<resp>ELTE Népdalkorpusz conversion</resp>
					<persName>
						<surname>Horváth</surname>
						<forename>Péter</forename>
					</persName>
					<persName>
						<surname>Palkó</surname>
						<forename>Gábor</forename>
						<ref target="https://viaf.org/viaf/65989506"/>
					</persName>
				</respStmt>
			</titleStmt>
			<extent>
				<measure unit="words">31</measure>
			</extent>
			<publicationStmt>
				<p>Published as part of ELTE Népdalkorpusz</p>
			</publicationStmt>
			<sourceDesc>
				<bibl>
					<title>[Mikor élő voltam, élőket tápláltam; …]</title>
					<bibl type="digitalEdition">
						<title>Magyar népdalok</title>
						<respStmt>
							<resp>editing and selection</resp>
							<persName>
								<surname>Ortutay</surname>
								<forename>Gyula</forename>
								<ref target="http://viaf.org/viaf/39752542"/>
							</persName>
							<persName>
								<surname>Katona</surname>
								<forename>Imre</forename>
								<ref target="http://viaf.org/viaf/42247938"/>
							</persName>
						</respStmt>
						<pubPlace>Budapest</pubPlace>
						<publisher>Neumann Kht.</publisher>
						<date when="2000">2000</date>
						<ref target="https://mek.oszk.hu/06200/06234"/>
					</bibl>
					<bibl type="printEdition">
						<title>Magyar népdalok</title>
						<respStmt>
							<resp>editing and selection</resp>
							<persName>
								<surname>Ortutay</surname>
								<forename>Gyula</forename>
								<ref target="http://viaf.org/viaf/39752542"/>
							</persName>
							<persName>
								<surname>Katona</surname>
								<forename>Imre</forename>
								<ref target="http://viaf.org/viaf/42247938"/>
							</persName>
						</respStmt>
						<pubPlace>Budapest</pubPlace>
						<publisher>Szépirodalmi Kiadó</publisher>
						<date when="1976">1976</date>
					</bibl>
				</bibl>
			</sourceDesc>
		</fileDesc>
		<encodingDesc>
			<projectDesc>
				<p>ELTE Népdalkorpusz - automatic annotation</p>
			</projectDesc>
			<classDecl>
				<taxonomy xml:id="g">
					<category xml:id="g.p">
						<catDesc>poetry</catDesc>
						<category xml:id="g.pl">
							<catDesc>lyric poetry</catDesc>
						</category>
						<category xml:id="g.pn">
							<catDesc>narrative poetry</catDesc>
						</category>
					</category>
				</taxonomy>
			</classDecl>
		</encodingDesc>
		<profileDesc>
			<langUsage>
				<language ident="hu">Hungarian</language>
			</langUsage>
			<textClass>
				<catRef target="#g.p"/>
			</textClass>
		</profileDesc>
		<revisionDesc>
			<change when="2022-02-14">level1</change>
			<change when="2022-02-14">level2</change>
			<change when="2022-02-14">level3</change>
		</revisionDesc>
	</teiHeader>
    <text>
        <body>
            <div type="poem" div_numStanza="1" div_numLine="5" div_numWord="25" div_numSyll="51" div_numShortSyll="21" div_numLongSyll="30" div_rhyme="aaaab" div_syllPattern="12-12-12-12-3">
                <head type="title">[Mikor élő voltam, élőket tápláltam; …]</head>
                <lg xml:id="lg1" lg_numLine="5" lg_numWord="25" lg_numSyll="51" lg_numShortSyll="21" lg_numLongSyll="30" rhyme="aaaab" lg_syllPattern="12-12-12-12-3">
                    <l xml:id="l1" l_numWord="5" l_numSyll="12" l_numShortSyll="4" l_numLongSyll="8" real="001110111110">
                        <w xml:id="w1" lemma="mikor" pos="PRON" msd="Case=Nom|Number=Sing|Person=3|PronType=Int" w_numSyll="2" phonType="mixed" phonStruct="cfcbc">Mikor</w>
                        <w xml:id="w2" lemma="élő" pos="ADJ" msd="Case=Nom|Degree=Pos|Number=Sing" w_numSyll="2" phonType="high" phonStruct="FcF">élő</w>
                        <w xml:id="w3" lemma="van" pos="VERB" msd="Definite=Ind|Mood=Ind|Number=Sing|Person=1|Tense=Past|VerbForm=Fin|Voice=Act" w_numSyll="2" phonType="low" phonStruct="cbccbc">voltam</w>
                        <pc xml:id="pc1" pos="PUNCT" join="left">,</pc>
                        <w xml:id="w4" lemma="élő" pos="ADJ" msd="Case=Acc|Degree=Pos|Number=Plur" w_numSyll="3" phonType="high" phonStruct="FcFcfc">élőket</w>
                        <w xml:id="w5" lemma="táplál" pos="VERB" msd="Definite=Ind|Mood=Ind|Number=Sing|Person=1|Tense=Past|VerbForm=Fin|Voice=Act" w_numSyll="3" phonType="low" phonStruct="cBccBccbc">tápláltam</w>
                        <pc xml:id="pc2" pos="PUNCT" join="left">;</pc>
                    </l>
                    <l xml:id="l2" l_numWord="6" l_numSyll="12" l_numShortSyll="7" l_numLongSyll="5" real="100100100110">
                        <w xml:id="w6" lemma="holta" pos="NOUN" msd="Case=Nom|Number=Sing|Number[psor]=Sing|Person[psor]=1" w_numSyll="2" phonType="low" phonStruct="cbccbc">Holtom</w>
                        <w xml:id="w7" lemma="után" pos="ADP" msd="_" w_numSyll="2" phonType="low" phonStruct="bcBc">után</w>
                        <w xml:id="w8" lemma="pedig" pos="CONJ" msd="_" w_numSyll="2" phonType="high" phonStruct="cfcfc">pedig</w>
                        <w xml:id="w9" lemma="én" pos="PRON" msd="Case=Nom|Number=Sing|Person=1|PronType=Prs" w_numSyll="1" phonType="high" phonStruct="Fc">én</w>
                        <w xml:id="w10" lemma="eleven" pos="ADJ" msd="Case=Nom|Degree=Pos|Number=Sing" w_numSyll="3" phonType="high" phonStruct="fcfcfc">eleven</w>
                        <w xml:id="w11" lemma="jár" pos="VERB" msd="Definite=Ind|Mood=Ind|Number=Sing|Person=1|Tense=Past|VerbForm=Fin|Voice=Act" w_numSyll="2" phonType="low" phonStruct="cBccbc">jártam</w>
                        <pc xml:id="pc3" pos="PUNCT" join="left">:</pc>
                    </l>
                    <l xml:id="l3" l_numWord="6" l_numSyll="12" l_numShortSyll="3" l_numLongSyll="9" real="111001111110">
                        <w xml:id="w12" lemma="én" pos="PRON" msd="Case=Nom|Number=Sing|Person=1|PronType=Prs" w_numSyll="1" phonType="high" phonStruct="Fc">Én</w>
                        <w xml:id="w13" lemma="még" pos="ADV" msd="_" w_numSyll="1" phonType="high" phonStruct="cFc">még</w>
                        <w xml:id="w14" lemma="holta" pos="NOUN" msd="Case=Nom|Number=Sing|Number[psor]=Sing|Person[psor]=1" w_numSyll="2" phonType="low" phonStruct="cbccbc">holtom</w>
                        <w xml:id="w15" lemma="után" pos="ADP" msd="_" w_numSyll="2" phonType="low" phonStruct="bcBc">után</w>
                        <w xml:id="w16" lemma="élő" pos="ADJ" msd="Case=Acc|Degree=Pos|Number=Plur" w_numSyll="3" phonType="high" phonStruct="FcFcfc">élőket</w>
                        <w xml:id="w17" lemma="hordoz" pos="VERB" msd="Definite=Ind|Mood=Ind|Number=Sing|Person=1|Tense=Past|VerbForm=Fin|Voice=Act" w_numSyll="3" phonType="low" phonStruct="cbccbccbc">hordoztam</w>
                        <pc xml:id="pc4" pos="PUNCT" join="left">,</pc>
                    </l>
                    <l xml:id="l4" l_numWord="7" l_numSyll="12" l_numShortSyll="5" l_numLongSyll="7" real="110011110010">
                        <w xml:id="w18" lemma="így" pos="CONJ" msd="_" w_numSyll="1" phonType="high" phonStruct="Fc">Így</w>
                        <w xml:id="w19" lemma="holta" pos="NOUN" msd="Case=Nom|Number=Sing|Number[psor]=Sing|Person[psor]=1" w_numSyll="2" phonType="low" phonStruct="cbccbc">holtom</w>
                        <w xml:id="w20" lemma="után" pos="ADP" msd="_" w_numSyll="2" phonType="low" phonStruct="bcBc">után</w>
                        <w xml:id="w21" lemma="is" pos="ADV" msd="_" w_numSyll="1" phonType="high" phonStruct="fc">is</w>
                        <w xml:id="w22" lemma="nem" pos="ADV" msd="PronType=Neg" w_numSyll="1" phonType="high" phonStruct="cfc">nem</w>
                        <w xml:id="w23" lemma="van" pos="VERB" msd="Definite=Ind|Mood=Ind|Number=Sing|Person=3|Tense=Past|VerbForm=Fin|Voice=Act" w_numSyll="1" phonType="low" phonStruct="cbcc">volt</w>
                        <w xml:id="w24" lemma="nyugodalom" pos="NOUN" msd="Case=Nom|Number=Sing|Number[psor]=Sing|Person[psor]=1" w_numSyll="4" phonType="low" phonStruct="cbcbcbccbc">nyugodalmam</w>
                        <pc xml:id="pc5" pos="PUNCT" join="left">.</pc>
                    </l>
                    <l xml:id="l5" l_numWord="1" l_numSyll="3" l_numShortSyll="2" l_numLongSyll="1" real="001">
                        <pc xml:id="pc6" pos="PUNCT" join="">(</pc>
                        <w xml:id="w25" lemma="fahajó" pos="NOUN" msd="Case=Nom|Number=Sing" w_numSyll="3" phonType="low" phonStruct="cbcbcB">Fahajó</w>
                        <pc xml:id="pc7" pos="PUNCT" join="left">)</pc>
                    </l>
                </lg>
            </div>
            <rhymePairs>
                <rhymePair target="#w5 #w11">
                    <firstRhyme rhyme_lemma="táplál" rhyme_pos="VERB" rhyme_msd="Definite=Ind|Mood=Ind|Number=Sing|Person=1|Tense=Past|VerbForm=Fin|Voice=Act" rhyme_numSyll="3" rhyme_phonType="low" rhyme_phonStruct="cBccBccbc">tápláltam</firstRhyme>
                    <secondRhyme rhyme_lemma="jár" rhyme_pos="VERB" rhyme_msd="Definite=Ind|Mood=Ind|Number=Sing|Person=1|Tense=Past|VerbForm=Fin|Voice=Act" rhyme_numSyll="2" rhyme_phonType="low" rhyme_phonStruct="cBccbc">jártam</secondRhyme>
                </rhymePair>
                <rhymePair target="#w11 #w17">
                    <firstRhyme rhyme_lemma="jár" rhyme_pos="VERB" rhyme_msd="Definite=Ind|Mood=Ind|Number=Sing|Person=1|Tense=Past|VerbForm=Fin|Voice=Act" rhyme_numSyll="2" rhyme_phonType="low" rhyme_phonStruct="cBccbc">jártam</firstRhyme>
                    <secondRhyme rhyme_lemma="hordoz" rhyme_pos="VERB" rhyme_msd="Definite=Ind|Mood=Ind|Number=Sing|Person=1|Tense=Past|VerbForm=Fin|Voice=Act" rhyme_numSyll="3" rhyme_phonType="low" rhyme_phonStruct="cbccbccbc">hordoztam</secondRhyme>
                </rhymePair>
                <rhymePair target="#w17 #w24">
                    <firstRhyme rhyme_lemma="hordoz" rhyme_pos="VERB" rhyme_msd="Definite=Ind|Mood=Ind|Number=Sing|Person=1|Tense=Past|VerbForm=Fin|Voice=Act" rhyme_numSyll="3" rhyme_phonType="low" rhyme_phonStruct="cbccbccbc">hordoztam</firstRhyme>
                    <secondRhyme rhyme_lemma="nyugodalom" rhyme_pos="NOUN" rhyme_msd="Case=Nom|Number=Sing|Number[psor]=Sing|Person[psor]=1" rhyme_numSyll="4" rhyme_phonType="low" rhyme_phonStruct="cbcbcbccbc">nyugodalmam</secondRhyme>
                </rhymePair>
            </rhymePairs>
            <alliterations>
                <alliteration target="#w2 #w3 #w4" allStruct="ana" posTags="ADJ VERB ADJ" msdTags="Case=Nom|Degree=Pos|Number=Sing Definite=Ind|Mood=Ind|Number=Sing|Person=1|Tense=Past|VerbForm=Fin|Voice=Act Case=Acc|Degree=Pos|Number=Plur" lemmas="élő van élő">élő voltam élőket</alliteration>
                <alliteration target="#w17 #w18 #w19" allStruct="ana" posTags="VERB CONJ NOUN" msdTags="Definite=Ind|Mood=Ind|Number=Sing|Person=1|Tense=Past|VerbForm=Fin|Voice=Act _ Case=Nom|Number=Sing|Number[psor]=Sing|Person[psor]=1" lemmas="hordoz így holta">hordoztam Így holtom</alliteration>
            </alliterations>
        </body>
    </text>
</exist>